MANIFEST.in
README.md
setup.cfg
setup.py
versioneer.py
SHARPpy.egg-info/PKG-INFO
SHARPpy.egg-info/SOURCES.txt
SHARPpy.egg-info/dependency_links.txt
SHARPpy.egg-info/entry_points.txt
SHARPpy.egg-info/requires.txt
SHARPpy.egg-info/top_level.txt
datasources/__init__.py
datasources/available.py
datasources/data_source.py
runsharp/SHARPpy.py
runsharp/__init__.py
runsharp/full_gui.py
sharppy/__init__.py
sharppy/_sharppy_version.py
sharppy/_version.py
sharppy/gui.py
sharppy/sounding.py
sharppy/databases/__init__.py
sharppy/databases/inset_data.py
sharppy/databases/pwv.py
sharppy/databases/sars.py
sharppy/databases/sars_cal.py
sharppy/io/__init__.py
sharppy/io/arw_decoder.py
sharppy/io/buf_decoder.py
sharppy/io/csv.py
sharppy/io/decoder.py
sharppy/io/pecan_decoder.py
sharppy/io/qc_tools.py
sharppy/io/spc_decoder.py
sharppy/io/uwyo_decoder.py
sharppy/plot/__init__.py
sharppy/plot/skew.py
sharppy/sharptab/__init__.py
sharppy/sharptab/constants.py
sharppy/sharptab/fire.py
sharppy/sharptab/interp.py
sharppy/sharptab/params.py
sharppy/sharptab/prof_collection.py
sharppy/sharptab/profile.py
sharppy/sharptab/thermo.py
sharppy/sharptab/utils.py
sharppy/sharptab/watch_type.py
sharppy/sharptab/winds.py
sharppy/viz/SPCWindow.py
sharppy/viz/__init__.py
sharppy/viz/advection.py
sharppy/viz/analogues.py
sharppy/viz/barbs.py
sharppy/viz/draggable.py
sharppy/viz/ensemble.py
sharppy/viz/fire.py
sharppy/viz/generic.py
sharppy/viz/hodo.py
sharppy/viz/kinematics.py
sharppy/viz/map.py
sharppy/viz/preferences.py
sharppy/viz/ship.py
sharppy/viz/skew.py
sharppy/viz/slinky.py
sharppy/viz/speed.py
sharppy/viz/srwinds.py
sharppy/viz/stp.py
sharppy/viz/stpef.py
sharppy/viz/thermo.py
sharppy/viz/thetae.py
sharppy/viz/vrot.py
sharppy/viz/watch.py
sharppy/viz/winter.py
sutils/__init__.py
sutils/async.py
sutils/async_threads.py
sutils/config.py
sutils/frozenutils.py
sutils/progress.py
sutils/utils.py
sutils/ver_updates.py